Metadata-Version: 2.1
Name: safebox
Version: 20210225111444
Summary: A safe waay to store your Python application credetials
Home-page: https://github.com/MMichels/safebox
Author: Mateus Michels de Oliveira
Author-email: michels09@hotmail.com
License: UNKNOWN
Platform: UNKNOWN
Requires: setuptools
Requires: wheel
Requires: Cython
